{
    "$schema": "https://schema.management.azure.com/schemas/2019-08-01/managementGroupDeploymentTemplate.json#",
    "contentVersion": "1.0.0.0",
    "parameters": {
        "topLevelManagementGroupPrefix": {
            "type": "string",
            "maxLength": 10,
            "metadata": {
                "description": "Provide a prefix (max 10 characters, unique at tenant-scope) for the Management Group hierarchy and other resources created as part of Afh."
            }
        },
        "enforcementMode": {
            "type": "string",
            "allowedValues": [
                "Default",
                "DoNotEnforce"
            ],
            "defaultValue": "Default"
        },
        "location": {
            "type": "string"
        }
    },
    "variables": {
        "policyDefinitions": {
            "deployNwResourceGroup": "[concat('/providers/Microsoft.Management/managementGroups/', parameters('topLevelManagementGroupPrefix'), '/providers/Microsoft.Authorization/policyDefinitions/Dine-NWRg')]"
        },
        "policyAssignmentNames": {
            "deployNwResourceGroup": "Deploy-Nw-ResourceGroup",
            "description": "Create Resource Group for Network Watcher in the subscriptions.",
            "displayName": "Create Resource Group for Network Watcher in the subscriptions."
        },
        "rbacOwner": "8e3af657-a8ff-443c-a75c-2fe8c4bcb635",
        "roleAssignmentNames": {
            "deployNwResourceGroup": "[guid(concat(parameters('toplevelManagementGroupPrefix'), deployment().name, variables('policyAssignmentNames').deployNwResourceGroup))]"
        }
    },
    "resources": [
        {
            "type": "Microsoft.Authorization/policyAssignments",
            "apiVersion": "2019-09-01",
            "name": "[variables('policyAssignmentNames').deployNwResourceGroup]",
            "location": "[deployment().location]",
            "identity": {
                "type": "SystemAssigned"
            },
            "properties": {
                "description": "[variables('policyAssignmentNames').description]",
                "displayName": "[variables('policyAssignmentNames').displayName]",
                "policyDefinitionId": "[variables('policyDefinitions').deployNwResourceGroup]",
                "enforcementMode": "[parameters('enforcementMode')]",
                "parameters": {
                    "location": {
                        "value": "[parameters('location')]"
                    }
                }
            }
        },
        {
            "type": "Microsoft.Authorization/roleAssignments",
            "apiVersion": "2019-04-01-preview",
            "name": "[variables('roleAssignmentNames').deployNwResourceGroup]",
            "dependsOn": [
                "[variables('policyAssignmentNames').deployNwResourceGroup]"
            ],
            "properties": {
                "principalType": "ServicePrincipal",
                "roleDefinitionId": "[concat('/providers/Microsoft.Authorization/roleDefinitions/', variables('rbacOwner'))]",
                "principalId": "[toLower(reference(concat('/providers/Microsoft.Authorization/policyAssignments/', variables('policyAssignmentNames').deployNwResourceGroup), '2019-09-01', 'Full' ).identity.principalId)]"
            }
        }        
    ],
    "outputs": {}
}